LbProdRun/__init__.py
LbProdRun/__main__.py
LbProdRun/models.py
lbprodrun-1.12.4.dist-info/licenses/LICENSE
lbprodrun-1.12.4.dist-info/METADATA
lbprodrun-1.12.4.dist-info/WHEEL
lbprodrun-1.12.4.dist-info/entry_points.txt
lbprodrun-1.12.4.dist-info/top_level.txt
lbprodrun-1.12.4.dist-info/RECORD
