Metadata-Version: 2.4
Name: LbProdRun
Version: 1.12.4
Summary: CLI for running LHCb applications from LHCbDIRAC
License: GPL-3.0-only
Project-URL: Homepage, https://gitlab.cern.ch/lhcb-core/lbprodrun
Classifier: License :: OSI Approved :: GNU General Public License v3 (GPLv3)
Classifier: Programming Language :: Python :: 3
Requires-Python: >=3.9
License-File: LICENSE
Requires-Dist: click>=8.0
Requires-Dist: lbenv
Requires-Dist: pydantic>=1.10
Requires-Dist: typer>=0.4.1
Requires-Dist: packaging
Requires-Dist: pyyaml>=6.0
Requires-Dist: LbCondaWrappers
Provides-Extra: testing
Requires-Dist: pytest; extra == "testing"
Requires-Dist: pytest-cov; extra == "testing"
Requires-Dist: zstandard; extra == "testing"
Provides-Extra: mypy
Requires-Dist: mypy; extra == "mypy"
Requires-Dist: types-PyYAML; extra == "mypy"
Dynamic: license-file
